LICENSE
README.md
setup.py
haibao/__init__.py
haibao/tools.py
haibao.egg-info/PKG-INFO
haibao.egg-info/SOURCES.txt
haibao.egg-info/dependency_links.txt
haibao.egg-info/requires.txt
haibao.egg-info/top_level.txt