Metadata-Version: 2.1
Name: haibao
Version: 1.3.1
Summary: seal haibao tools
Home-page: UNKNOWN
Author: seal
Author-email: seal.xu@qq.com
License: UNKNOWN
Platform: UNKNOWN
Classifier: Programming Language :: Python :: 3
Classifier: License :: OSI Approved :: MIT License
Classifier: Operating System :: OS Independent
Requires-Python: >=3.6
